odoo/addons/pos_container_deposit/README.rst
odoo/addons/pos_container_deposit/__init__.py
odoo/addons/pos_container_deposit/__manifest__.py
odoo/addons/pos_container_deposit/demo/product_product.xml
odoo/addons/pos_container_deposit/i18n/it.po
odoo/addons/pos_container_deposit/i18n/nl.po
odoo/addons/pos_container_deposit/i18n/pos_container_deposit.pot
odoo/addons/pos_container_deposit/models/__init__.py
odoo/addons/pos_container_deposit/models/pos_session.py
odoo/addons/pos_container_deposit/models/product_product.py
odoo/addons/pos_container_deposit/models/product_template.py
odoo/addons/pos_container_deposit/readme/CONFIGURE.rst
odoo/addons/pos_container_deposit/readme/CONTEXT.rst
odoo/addons/pos_container_deposit/readme/CONTRIBUTORS.rst
odoo/addons/pos_container_deposit/readme/DESCRIPTION.rst
odoo/addons/pos_container_deposit/readme/USAGE.rst
odoo/addons/pos_container_deposit/static/description/icon.png
odoo/addons/pos_container_deposit/static/description/index.html
odoo/addons/pos_container_deposit/static/src/js/components.js
odoo/addons/pos_container_deposit/static/src/js/models.js
odoo/addons/pos_container_deposit/static/tests/tours/pos_container_deposit_tour.js
odoo/addons/pos_container_deposit/tests/__init__.py
odoo/addons/pos_container_deposit/tests/test_pos_container_deposit.py
odoo/addons/pos_container_deposit/tests/test_pos_container_deposit_frontend.py
odoo/addons/pos_container_deposit/views/product_template.xml
odoo_addon_pos_container_deposit-16.0.1.0.0.5.dist-info/METADATA
odoo_addon_pos_container_deposit-16.0.1.0.0.5.dist-info/WHEEL
odoo_addon_pos_container_deposit-16.0.1.0.0.5.dist-info/top_level.txt
odoo_addon_pos_container_deposit-16.0.1.0.0.5.dist-info/RECORD
