Metadata-Version: 2.1
Name: odoo-addon-pos_container_deposit
Version: 16.0.1.0.0.5
Summary: This module is used to manage container deposits for products in Point of Sale.
Home-page: https://github.com/OCA/pos
Author: Sunflower IT, Open2bizz, Odoo Community Association (OCA)
Author-email: support@odoo-community.org
License: AGPL-3
Classifier: Programming Language :: Python
Classifier: Framework :: Odoo
Classifier: Framework :: Odoo :: 16.0
Classifier: License :: OSI Approved :: GNU Affero General Public License v3
Requires-Python: >=3.10
Requires-Dist: odoo<16.1dev,>=16.0a
